<?xmlversion="1.0"encoding="utf-8"?>
<flectra>
    <recordid="product_template_view_form"model="ir.ui.view">
        <fieldname="name">product.template.view.form.inherit.website_membership</field>
        <fieldname="model">product.template</field>
        <fieldname="inherit_id"ref="membership.membership_products_form"/>
        <fieldname="arch"type="xml">
            <fieldname="active"position="after">
                <fieldname="website_published"/>
                <fieldname="website_sequence"groups="base.group_no_one"/>
            </field>
        </field>
    </record>

    <recordid="product_template_view_tree"model="ir.ui.view">
        <fieldname="name">product.template.view.tree.inherit.website_membership</field>
        <fieldname="model">product.template</field>
        <fieldname="inherit_id"ref="membership.membership_products_tree"/>
        <fieldname="arch"type="xml">
            <fieldname="name"position="before">
                <fieldname="website_sequence"widget="handle"/>
            </field>
        </field>
    </record>
</flectra>
