<?xmlversion="1.0"encoding="utf-8"?>
<flectra>

    <templateid="assets_frontend"inherit_id="website.assets_frontend"name="Wishlistassetsfrontend">
        <xpathexpr="."position="inside">
            <linkrel="stylesheet"type="text/scss"href="/website_sale_wishlist/static/src/scss/website_sale_wishlist.scss"/>
            <scripttype="text/javascript"src="/website_sale_wishlist/static/src/js/website_sale_wishlist.js"></script>
        </xpath>
    </template>

    <templateid="assets_tests"name="WebsiteSaleWishlistAssetsTests"inherit_id="web.assets_tests">
        <xpathexpr="."position="inside">
            <scripttype="text/javascript"src="/website_sale_wishlist/static/tests/tours/website_sale_wishlist.js"></script>
            <scripttype="text/javascript"src="/website_sale_wishlist/static/tests/tours/website_sale_wishlist_admin.js"></script>
        </xpath>
    </template>

    <templateid="add_to_wishlist"inherit_id="website_sale.products_item"customize_show="True"name="WishlistButton"priority="20">
        <xpathexpr="//div[hasclass('o_wsale_product_btn')]"position="inside">
            <tt-set="in_wish"t-value="product._is_in_wishlist()"/>
            <tt-set="product_variant_id"t-value="product._get_first_possible_variant_id()"/>
            <buttont-if="product_variant_id"type="button"role="button"class="btnbtn-secondaryo_add_wishlist"t-att-disabled='in_wishorNone'title="AddtoWishlist"t-att-data-product-template-id="product.id"t-att-data-product-product-id="product_variant_id"data-action="o_wishlist"><spanclass="fafa-heart"role="img"aria-label="Addtowishlist"></span></button>
        </xpath>
    </template>

    <templateid="product_add_to_wishlist"inherit_id="website_sale.product"customize_show="True"name="WishlistButton"priority="20">
        <xpathexpr="//div[@id='product_option_block']"position="inside">
            <tt-set="product_variant"t-value="product_variantorproduct._create_first_product_variant()"/>
            <tt-set="in_wish"t-value="product_variantandproduct_variant._is_in_wishlist()"/>
            <buttont-if="product_variant"type="button"role="button"class="btnbtn-linkmt16o_add_wishlist_dyn"t-att-disabled='in_wishorNone't-att-data-product-template-id="product.id"t-att-data-product-product-id="product_variant.id"data-action="o_wishlist"><spanclass="fafa-heart"role="img"aria-label="Addtowishlist"></span>Addtowishlist</button>
        </xpath>
    </template>

    <templateid="header_wishlist_link"name="HeaderWishlistLink">
        <tt-set="wishcount"t-value="len(request.env['product.wishlist'].current())"/>
        <tt-set="show_wishes"t-value="True"/>
        <lit-attf-class="o_wsale_my_wish#{notshow_wishesand'd-none'}#{_item_class}">
            <ahref="/shop/wishlist"t-attf-class="#{_link_class}">
                <it-if="_icon"class="fafa-1xfa-heart"/>
                <spant-if="_text">Wishlist</span>
                <supt-esc="wishcount"t-attf-class="my_wish_quantityo_animate_blinkbadgebadge-primary"/>
            </a>
        </li>
    </template>

    <templateid="header_hide_empty_wishlist_link"inherit_id="website_sale_wishlist.header_wishlist_link">
        <xpathexpr="//t[@t-set='show_wishes']"position="after">
            <tt-set="show_wishes"t-value="show_wishesandwishcount>0"/>
        </xpath>
        <xpathexpr="//li[contains(@t-attf-class,'o_wsale_my_wish')]"position="attributes">
            <attributename="t-attf-class"add="o_wsale_my_wish_hide_empty"separator=""/>
        </xpath>
    </template>

    <templateid="template_header_default"inherit_id="website_sale.template_header_default">
        <xpathexpr="//t[@t-call='website_sale.header_cart_link']"position="after">
            <tt-call="website_sale_wishlist.header_wishlist_link">
                <tt-set="_icon"t-value="True"/>
                <tt-set="_item_class"t-value="'nav-itemmr-lg-3'"/>
                <tt-set="_link_class"t-value="'nav-link'"/>
            </t>
        </xpath>
    </template>

    <templateid="template_header_hamburger"inherit_id="website_sale.template_header_hamburger">
        <xpathexpr="//t[@t-call='website_sale.header_cart_link']"position="after">
            <tt-call="website_sale_wishlist.header_wishlist_link">
                <tt-set="_text"t-value="True"/>
                <tt-set="_item_class"t-value="'nav-item'"/>
                <tt-set="_link_class"t-value="'nav-link'"/>
            </t>
        </xpath>
    </template>

    <templateid="template_header_vertical"inherit_id="website_sale.template_header_vertical">
        <xpathexpr="//t[@t-call='website_sale.header_cart_link']"position="after">
            <tt-call="website_sale_wishlist.header_wishlist_link">
                <tt-set="_icon"t-value="True"/>
                <tt-set="_item_class"t-value="'nav-itemml-lg-3'"/>
                <tt-set="_link_class"t-value="'nav-link'"/>
            </t>
        </xpath>
    </template>

    <templateid="template_header_sidebar"inherit_id="website_sale.template_header_sidebar">
        <xpathexpr="//t[@t-call='website_sale.header_cart_link']"position="after">
            <tt-call="website_sale_wishlist.header_wishlist_link">
                <tt-set="_icon"t-value="True"/>
                <tt-set="_text"t-value="True"/>
                <tt-set="_item_class"t-value="'nav-item'"/>
                <tt-set="_link_class"t-value="'nav-link'"/>
            </t>
        </xpath>
    </template>

    <templateid="template_header_slogan"inherit_id="website_sale.template_header_slogan">
        <xpathexpr="//t[@t-call='website_sale.header_cart_link']"position="after">
            <tt-call="website_sale_wishlist.header_wishlist_link">
                <tt-set="_icon"t-value="True"/>
                <tt-set="_item_class"t-value="'nav-itemml-3'"/>
                <tt-set="_link_class"t-value="'nav-link'"/>
            </t>
        </xpath>
    </template>

    <templateid="template_header_contact"inherit_id="website_sale.template_header_contact">
        <xpathexpr="//t[@t-call='website_sale.header_cart_link']"position="after">
            <tt-call="website_sale_wishlist.header_wishlist_link">
                <tt-set="_icon"t-value="True"/>
                <tt-set="_item_class"t-value="'nav-itemml-lg-3'"/>
                <tt-set="_link_class"t-value="'nav-link'"/>
            </t>
        </xpath>
    </template>

    <templateid="template_header_minimalist"inherit_id="website_sale.template_header_minimalist">
        <xpathexpr="//t[@t-call='website_sale.header_cart_link']"position="after">
            <tt-call="website_sale_wishlist.header_wishlist_link">
                <tt-set="_icon"t-value="True"/>
                <tt-set="_item_class"t-value="'nav-item'"/>
                <tt-set="_link_class"t-value="'nav-linkml-3'"/>
            </t>
        </xpath>
    </template>

    <templateid="template_header_boxed"inherit_id="website_sale.template_header_boxed">
        <xpathexpr="//t[@t-call='website_sale.header_cart_link']"position="after">
            <tt-call="website_sale_wishlist.header_wishlist_link">
                <tt-set="_text"t-value="True"/>
                <tt-set="_item_class"t-value="'nav-itemml-lg-3'"/>
                <tt-set="_link_class"t-value="'nav-link'"/>
            </t>
        </xpath>
    </template>

    <templateid="template_header_centered_logo"inherit_id="website_sale.template_header_centered_logo">
        <xpathexpr="//t[@t-call='website_sale.header_cart_link']"position="after">
            <tt-call="website_sale_wishlist.header_wishlist_link">
                <tt-set="_icon"t-value="True"/>
                <tt-set="_item_class"t-value="'nav-itemml-1'"/>
                <tt-set="_link_class"t-value="'nav-link'"/>
            </t>
        </xpath>
    </template>

    <templateid="template_header_image"inherit_id="website_sale.template_header_image">
        <xpathexpr="//t[@t-call='website_sale.header_cart_link']"position="after">
            <tt-call="website_sale_wishlist.header_wishlist_link">
                <tt-set="_icon"t-value="True"/>
                <tt-set="_item_class"t-value="'nav-itemml-lg-2'"/>
                <tt-set="_link_class"t-value="'nav-link'"/>
            </t>
        </xpath>
    </template>

    <templateid="template_header_hamburger_full"inherit_id="website_sale.template_header_hamburger_full">
        <xpathexpr="//t[@t-call='website_sale.header_cart_link']"position="after">
            <tt-call="website_sale_wishlist.header_wishlist_link">
                <tt-set="_icon"t-value="True"/>
                <tt-set="_item_class"t-value="'nav-itemml-lg-2'"/>
                <tt-set="_link_class"t-value="'nav-link'"/>
            </t>
        </xpath>
    </template>

    <templateid="template_header_magazine"inherit_id="website_sale.template_header_magazine">
        <xpathexpr="//t[@t-call='website_sale.header_cart_link']"position="after">
            <tt-call="website_sale_wishlist.header_wishlist_link">
                <tt-set="_text"t-value="True"/>
                <tt-set="_item_class"t-value="'nav-item'"/>
                <tt-set="_link_class"t-value="'nav-link'"/>
            </t>
        </xpath>
    </template>

    <templateid="product_wishlist"name="WishlistPage">
        <tt-call="website.layout">
            <tt-set="additional_title">ShopWishlist</t>
            <divid="wrap"class="js_sale">
                <divclass="oe_structure"id="oe_structure_website_sale_wishlist_product_wishlist_1"/>
                <divclass="containeroe_website_sale">
                    <sectionclass="containerwishlist-section">
                        <h3>MyWishlist</h3>
                        <divclass="checkbox">
                            <labelclass='text-muted'><inputtype="checkbox"id='b2b_wish'value="1"class="mr8"/>Addproducttomycartbutkeepitinmywishlist</label>
                        </div>
                        <tableclass="tabletable-borderedtable-stripedtable-hovertext-centermt16table-comparator"style="table-layout:auto"id="o_comparelist_table">
                            <body>
                                <tt-foreach="wishes"t-as="wish">
                                    <trt-att-data-wish-id='wish.id't-att-data-product-id='wish.product_id.id'>
                                        <tdclass='td-img'>
                                            <at-att-href="wish.product_id.website_url">
                                                <imgt-attf-src="/web/image/product.product/#{wish.product_id.id}/image_128"class="imgimg-fluid"style="margin:auto;"alt="Productimage"/>
                                            </a>
                                        </td>
                                        <tdclass='text-left'>
                                            <strong><at-att-href="wish.product_id.website_url"><tt-esc="wish.product_id.display_name"/></a></strong>
                                            <smallclass='d-noned-md-block'><pt-field="wish.product_id.description_sale"class="text-muted"/></small>
                                            <buttontype="button"class="btnbtn-linko_wish_rmno-decoration"><small><iclass='fafa-trash-o'></i>Remove</small></button>
                                        </td>
                                        <td>
                                            <tt-set="combination_info"t-value="wish.product_id._get_combination_info_variant()"/>
                                            <tt-esc="combination_info['price']"t-options="{'widget':'monetary','display_currency':website.pricelist_id.currency_id}"/>
                                        </td>
                                        <tdclass='text-centertd-wish-btn'>
                                            <inputname="product_id"t-att-value="wish.product_id.id"type="hidden"/>
                                            <buttontype="button"role="button"class="btnbtn-secondarybtn-blocko_wish_addmb4">Add<spanclass='d-noned-md-inline'>toCart</span></button>
                                        </td>
                                    </tr>
                                </t>
                            </body>
                        </table>
                    </section>
                </div>
            </div>
        </t>
    </template>

</flectra>
