<?xmlversion="1.0"encoding="utf-8"?>
<flectra>
    <recordid="event_registration_view_form_inherit_question"model="ir.ui.view">
        <fieldname="name">event.registration.view.form.inherit.question</field>
        <fieldname="model">event.registration</field>
        <fieldname="inherit_id"ref="event.view_event_registration_form"/>
        <fieldname="arch"type="xml">
            <sheetposition="inside">
                <notebook>
                    <pagestring="Questions"name="questions">
                        <fieldname="registration_answer_ids"widget="one2many">
                            <treeeditable="bottom">
                                <fieldname="event_id"invisible="1"/>
                                <fieldname="question_id"domain="[('event_id','=',event_id)]"options="{'no_create':True}"/>
                                <fieldname="question_type"string="Type"/>
                                <fieldname="value_answer_id"
                                    attrs="{'invisible':[('question_type','!=','simple_choice')]}"
                                    domain="[('question_id','=',question_id)]"options="{'no_create':True}"/>
                                <fieldname="value_text_box"attrs="{'invisible':[('question_type','!=','text_box')]}"/>
                            </tree>
                        </field>
                    </page>
                </notebook>
            </sheet>
        </field>
    </record>
</flectra>
