<?xmlversion="1.0"encoding="utf-8"?>
<flectra>
    <datanoupdate="1">

        <!--AccountTaxGroup-->
        <recordid="tax_group_24"model="account.tax.group">
            <fieldname="name">VAT24%</field>
        </record>
        <recordid="tax_group_14"model="account.tax.group">
            <fieldname="name">VAT14%</field>
        </record>
        <recordid="tax_group_10"model="account.tax.group">
            <fieldname="name">VAT10%</field>
        </record>
        <recordid="tax_group_0"model="account.tax.group">
            <fieldname="name">VAT0%</field>
        </record>

    </data>
</flectra>
