<?xmlversion="1.0"encoding="utf-8"?>
<flectra>
    <!--account.tax.template(pre-2023)-->
    <recordid="tr_kdv_satis_sale_18"model="account.tax.template">
        <fieldname="sequence">11</field>
        <fieldname="description">KDV%18(sale)</field>
        <fieldname="name">KDV%18(sale)</field>
        <fieldname="price_include"eval="0"/>
        <fieldname="amount">18</field>
        <fieldname="amount_type">percent</field>
        <fieldname="type_tax_use">sale</field>
        <fieldname="chart_template_id"ref="l10ntr_tek_duzen_hesap"/>
        <fieldname="tax_group_id"ref="tax_group_kdv_18"/>
        <fieldname="invoice_repartition_line_ids"eval="[(5,0,0),
            (0,0,{
                'factor_percent':100,
                'repartition_type':'base',
            }),
            (0,0,{
                'factor_percent':100,
                'repartition_type':'tax',
                'account_id':ref('tr391'),
            }),
        ]"/>
        <fieldname="refund_repartition_line_ids"eval="[(5,0,0),
            (0,0,{
                'factor_percent':100,
                'repartition_type':'base',
            }),
            (0,0,{
                'factor_percent':100,
                'repartition_type':'tax',
                'account_id':ref('tr191'),
            }),
        ]"/>
    </record>

    <recordid="tr_kdv_satis_purchase_18"model="account.tax.template">
        <fieldname="sequence">11</field>
        <fieldname="description">KDV%18(purchase)</field>
        <fieldname="name">KDV%18(purchase)</field>
        <fieldname="price_include"eval="0"/>
        <fieldname="amount">18</field>
        <fieldname="amount_type">percent</field>
        <fieldname="type_tax_use">purchase</field>
        <fieldname="chart_template_id"ref="l10ntr_tek_duzen_hesap"/>
        <fieldname="tax_group_id"ref="tax_group_kdv_18"/>
        <fieldname="invoice_repartition_line_ids"eval="[(5,0,0),
            (0,0,{
                'factor_percent':100,
                'repartition_type':'base',
            }),
            (0,0,{
                'factor_percent':100,
                'repartition_type':'tax',
                'account_id':ref('tr391'),
            }),
        ]"/>
        <fieldname="refund_repartition_line_ids"eval="[(5,0,0),
            (0,0,{
                'factor_percent':100,
                'repartition_type':'base',
            }),
            (0,0,{
                'factor_percent':100,
                'repartition_type':'tax',
                'account_id':ref('tr191'),
            }),
        ]"/>
    </record>

    <!--account.tax.template(introducedinJuly2023)-->
    <recordid="tr_kdv_satis_sale_20"model="account.tax.template">
        <fieldname="sequence">13</field>
        <fieldname="description">KDV20%</field>
        <fieldname="name">20%</field>
        <fieldname="price_include"eval="0"/>
        <fieldname="amount">20</field>
        <fieldname="amount_type">percent</field>
        <fieldname="type_tax_use">sale</field>
        <fieldname="chart_template_id"ref="l10ntr_tek_duzen_hesap"/>
        <fieldname="tax_group_id"ref="tax_group_kdv_20"/>
        <fieldname="invoice_repartition_line_ids"eval="[(5,0,0),
            (0,0,{
                'factor_percent':100,
                'repartition_type':'base',
            }),
            (0,0,{
                'factor_percent':100,
                'repartition_type':'tax',
                'account_id':ref('tr391'),
            }),
        ]"/>
        <fieldname="refund_repartition_line_ids"eval="[(5,0,0),
            (0,0,{
                'factor_percent':100,
                'repartition_type':'base',
            }),
            (0,0,{
                'factor_percent':100,
                'repartition_type':'tax',
                'account_id':ref('tr191'),
            }),
        ]"/>
    </record>

    <recordid="tr_kdv_satis_purchase_20"model="account.tax.template">
        <fieldname="sequence">14</field>
        <fieldname="description">KDV20%</field>
        <fieldname="name">20%</field>
        <fieldname="price_include"eval="0"/>
        <fieldname="amount">20</field>
        <fieldname="amount_type">percent</field>
        <fieldname="type_tax_use">purchase</field>
        <fieldname="chart_template_id"ref="l10ntr_tek_duzen_hesap"/>
        <fieldname="tax_group_id"ref="tax_group_kdv_20"/>
        <fieldname="invoice_repartition_line_ids"eval="[(5,0,0),
            (0,0,{
                'factor_percent':100,
                'repartition_type':'base',
            }),
            (0,0,{
                'factor_percent':100,
                'repartition_type':'tax',
                'account_id':ref('tr391'),
            }),
        ]"/>
        <fieldname="refund_repartition_line_ids"eval="[(5,0,0),
            (0,0,{
                'factor_percent':100,
                'repartition_type':'base',
            }),
            (0,0,{
                'factor_percent':100,
                'repartition_type':'tax',
                'account_id':ref('tr191'),
            }),
        ]"/>
    </record>
</flectra>
